alectryon/__init__.py
alectryon/__main__.py
alectryon/cli.py
alectryon/coq.py
alectryon/coqc_time.py
alectryon/core.py
alectryon/docutils.py
alectryon/html.py
alectryon/json.py
alectryon/latex.py
alectryon/literate.py
alectryon/markers.py
alectryon/minimal.py
alectryon/myst.py
alectryon/pygments.py
alectryon/pygments_lexer.py
alectryon/pygments_style.py
alectryon/serapi.py
alectryon/sexp.py
alectryon/sphinx.py
alectryon/transforms.py
alectryon/assets/alectryon.css
alectryon/assets/alectryon.js
alectryon/assets/alectryon.sty
alectryon/assets/docutils_basic.css
alectryon-1.4.0.dist-info/LICENSE
alectryon-1.4.0.dist-info/METADATA
alectryon-1.4.0.dist-info/WHEEL
alectryon-1.4.0.dist-info/entry_points.txt
alectryon-1.4.0.dist-info/top_level.txt
alectryon-1.4.0.dist-info/RECORD
