Metadata-Version: 2.1
Name: alectryon
Version: 1.4.0
Summary: A library to process Coq snippets embedded in documents, showing goals and messages for each Coq sentence.
Home-page: https://github.com/cpitclaudel/alectryon
Author: Clément Pit-Claudel
Author-email: clement.pitclaudel@live.com
License: MIT
Platform: UNKNOWN
Classifier: Development Status :: 5 - Production/Stable
Classifier: Intended Audience :: Science/Research
Classifier: License :: OSI Approved :: MIT License
Classifier: Operating System :: OS Independent
Classifier: Programming Language :: Python :: 3
Classifier: Topic :: Software Development :: Compilers
Classifier: Topic :: Text Editors :: Documentation
Classifier: Topic :: Text Processing :: Markup :: reStructuredText
Requires-Python: >=3.6
License-File: LICENSE
Requires-Dist: pygments
Requires-Dist: dominate
Requires-Dist: beautifulsoup4
Requires-Dist: docutils
Provides-Extra: full
Requires-Dist: myst-parser ; extra == 'full'
Requires-Dist: sphinx ; extra == 'full'
Provides-Extra: md
Requires-Dist: myst-parser ; extra == 'md'
Provides-Extra: sphinx
Requires-Dist: sphinx ; extra == 'sphinx'
